AoikArgUtil-0.3.0.dist-info/DESCRIPTION.rst
AoikArgUtil-0.3.0.dist-info/METADATA
AoikArgUtil-0.3.0.dist-info/RECORD
AoikArgUtil-0.3.0.dist-info/WHEEL
AoikArgUtil-0.3.0.dist-info/metadata.json
AoikArgUtil-0.3.0.dist-info/top_level.txt
aoikargutil/__init__.py
aoikargutil/aoikargutil.py
aoikargutil/aoikargutil_tests.py
